rikafirenet/__init__.py
rikafirenet/cli.py
rikafirenet/client.py
rikafirenet/const.py
rikafirenet/controls.py
rikafirenet/coordinator.py
rikafirenet/sensors.py
rikafirenet/stove.py
rikafirenet-0.1.0.dist-info/AUTHORS.rst
rikafirenet-0.1.0.dist-info/LICENSE
rikafirenet-0.1.0.dist-info/METADATA
rikafirenet-0.1.0.dist-info/WHEEL
rikafirenet-0.1.0.dist-info/entry_points.txt
rikafirenet-0.1.0.dist-info/top_level.txt
rikafirenet-0.1.0.dist-info/RECORD
