Metadata-Version: 2.1
Name: rikafirenet
Version: 0.1.0
Summary: Python package that dialogs with Rika pellet stove (under dev)
Home-page: https://github.com/mttng/rikafirenet
Author: Mathieu Tanguy
Author-email: mathieu@tanguym.eu
License: MIT license
Keywords: rikafirenet
Classifier: Development Status :: 2 - Pre-Alpha
Classifier: Intended Audience :: Developers
Classifier: License :: OSI Approved :: MIT License
Classifier: Natural Language :: English
Classifier: Programming Language :: Python :: 3
Classifier: Programming Language :: Python :: 3.6
Classifier: Programming Language :: Python :: 3.7
Classifier: Programming Language :: Python :: 3.8
Requires-Python: >=3.6
License-File: LICENSE
License-File: AUTHORS.rst
Requires-Dist: Click>=7.0
